ontopint/__init__.py
ontopint-0.1.1.dist-info/LICENSE
ontopint-0.1.1.dist-info/METADATA
ontopint-0.1.1.dist-info/WHEEL
ontopint-0.1.1.dist-info/top_level.txt
ontopint-0.1.1.dist-info/RECORD
