Metadata-Version: 2.1
Name: ontopint
Version: 0.1.1
Summary: A python package for reading units from a JSON-LD files and generating pint quantities.
Author: Fabian Kirchner, Simon Stier, Fabio Lopes, Despoina Adamopoulou, Samantha Pearman-Kanza
Author-email: Hampus Näsström <hampus.naesstroem@physik.hu-berlin.de>
Maintainer-email: Hampus Näsström <hampus.naesstroem@physik.hu-berlin.de>
License: MIT License
Project-URL: Homepage, https://github.com/hampusnasstrom/ontopint
Project-URL: Bug Tracker, https://github.com/hampusnasstrom/ontopint/issues
Classifier: Development Status :: 4 - Beta
Classifier: Programming Language :: Python :: 3
Classifier: Programming Language :: Python :: 3 :: Only
Classifier: License :: OSI Approved :: MIT License
License-File: LICENSE
Requires-Dist: rdflib
Requires-Dist: sparqlwrapper
Requires-Dist: pint
Requires-Dist: pyld
Requires-Dist: ucumvert
Provides-Extra: dev
Requires-Dist: pytest ; extra == 'dev'
Requires-Dist: deepdiff ; extra == 'dev'
